[
    {
        "id": 0,
        "label": "Гардиан 32.15",
        "code": "11"
    },
    {
        "id": 1,
        "label": "Гардиан 32.01 + 3 боченка",
        "code": "12"
    },
    {
        "id": 2,
        "label": "1 ригельный (+электрозащелка)",
        "code": "13"
    },
    {
        "id": 3,
        "label": "1 ригельный (+регулятор язычка) + Невидимка",
        "code": "14"
    },
    {
        "id": 4,
        "label": "1 ригельный (+электрозащелка) + Невидимка",
        "code": "15"
    },
    {
        "id": 5,
        "label": "1 ригельный (+электрозащелка) + Панель вызова",
        "code": "16"
    },
    {
        "id": 6,
        "label": "1 ригельный (+электрозащелка) + RFID-считка",
        "code": "17"
    },
    {
        "id": 7,
        "label": "1 ригельный (+электрозащелка) + BIO-считка",
        "code": "18"
    },
    {
        "id": 8,
        "label": "Гардиан 32.15 + Гардиан 30.01",
        "code": "21"
    },
    {
        "id": 9,
        "label": "Гардиан 32.01 + Гардиан 30.01 + 3 боченка",
        "code": "22"
    },
    {
        "id": 10,
        "label": "2 ригельных (+регулятор на нижнем) + Невидимка",
        "code": "23"
    },
    {
        "id": 11,
        "label": "2 ригельных (+электрозащелка) + Невидимка",
        "code": "24"
    },
    {
        "id": 12,
        "label": "2 ригельных (+электрозащелка) + Панель вызова",
        "code": "25"
    },
    {
        "id": 13,
        "label": "2 ригельных (+электрозащелка) + RFID-считка",
        "code": "26"
    },
    {
        "id": 14,
        "label": "2 ригельных (+электрозащелка) + BIO-считка",
        "code": "27"
    },
    {
        "id": 15,
        "label": "1 электромагнит ML350",
        "code": "31"
    },
    {
        "id": 16,
        "label": "2 электромагнита ML250",
        "code": "32"
    },
    {
        "id": 17,
        "label": "1 сдвиговый электромагнит",
        "code": "33"
    },
    {
        "id": 18,
        "label": "1 электрозадвижка (дэдболт)",
        "code": "34"
    },
    {
        "id": 18,
        "label": "1 кодово-механический",
        "code": "41"
    },
    {
        "id": 20,
        "label": "1 нажимная защелка",
        "code": "42"
    },
    {
        "id": 21,
        "label": "1 защелка-бочонок",
        "code": "43"
    }
]